pendragondi_cloud_audit/__init__.py
pendragondi_cloud_audit/auditor_core.py
pendragondi_cloud_audit/cli.py
pendragondi_cloud_audit/reporter.py
pendragondi_cloud_audit/providers/__init__.py
pendragondi_cloud_audit/providers/aws_s3.py
pendragondi_cloud_audit/providers/azure_blob.py
pendragondi_cloud_audit/providers/gcs.py
pendragondi_cloud_audit/providers/utils.py
pendragondi_cloud_audit-0.3.3.dist-info/licenses/LICENSE
pendragondi_cloud_audit-0.3.3.dist-info/METADATA
pendragondi_cloud_audit-0.3.3.dist-info/WHEEL
pendragondi_cloud_audit-0.3.3.dist-info/entry_points.txt
pendragondi_cloud_audit-0.3.3.dist-info/top_level.txt
pendragondi_cloud_audit-0.3.3.dist-info/RECORD
