Metadata-Version: 2.4
Name: pendragondi-cloud-audit
Version: 0.3.3
Summary: PendragonDI Cloud Audit – local tool to detect stale, redundant, or inefficient storage in cloud buckets.
Author-email: jinpendragon <pendragondi@pendragondi.dev>
License: MIT
Requires-Python: >=3.9
License-File: LICENSE
Requires-Dist: typer
Provides-Extra: aws
Requires-Dist: boto3; extra == "aws"
Provides-Extra: gcs
Requires-Dist: google-cloud-storage; extra == "gcs"
Provides-Extra: azure
Requires-Dist: azure-storage-blob; extra == "azure"
Provides-Extra: all
Requires-Dist: boto3; extra == "all"
Requires-Dist: google-cloud-storage; extra == "all"
Requires-Dist: azure-storage-blob; extra == "all"
Dynamic: license-file
